{"week1": {
"mon": [
{"cab": "510", "type": "Лек", "tch": "Смирнов Е.Е.", "name": "Информационные технологии"},
{"cab": "523", "type": "Лаб", "tch": "Смирнов Е.Е.", "name": "Информационные технологии, п/г 1"},
{"cab": "407", "type": "Пр", "tch": "препод. кафедры", "name": "Иностранный язык"},
{"cab": "515", "type": "Лек", "tch": "Семенов А.А.", "name": "Технология программирования"},
{"cab": "515", "type": "Лаб", "tch": "Семенов А.А.", "name": "Информационные системы и технологии в дизайне, п/г 1"},
{"cab": "", "type": "", "tch": "", "name": ""}
], "tue": [
{"cab": "", "type": "", "tch": "", "name": ""},
{"cab": "510", "type": "Лаб", "tch": "Семенов А.А.", "name": "Технология программирования, п/г 1"},
{"cab": "510", "type": "Лек", "tch": "Семенов А.А.", "name": "Информационные системы и технологии в дизайне"},
{"cab": "510", "type": "Лаб", "tch": "Семенов А.А.", "name": "Информационные системы и технологии в дизайне, п/г 2"},
{"cab": "510", "type": "Лаб", "tch": "Семенов А.А.", "name": "Технология программирования, п/г 2"},
{"cab": "", "type": "", "tch": "", "name": ""}
], "wed": [
{"cab": "", "type": "", "tch": "", "name": ""},
{"cab": "", "type": "", "tch": "", "name": ""},
{"cab": "сп. зал", "type": "пр.", "tch": "преп. каф. физич. культ.", "name": "Элективные дисциплины по физической культуре и спорту"},
{"cab": "1110", "type": "Лаб", "tch": "Мещеряков А.В.   Хейло С.В.", "name": "Прикладная механика"},
{"cab": "1611", "type": "Пр", "tch": "Бугримов А.Л.", "name": "Математика"},
{"cab": "", "type": "", "tch": "", "name": ""}
], "thu": [
{"cab": "1537", "type": "Лек", "tch": "Пухир В.М.", "name": "Философия"},
{"cab": "1205", "type": "Лек", "tch": "Суетин В.Ю.", "name": "Математика"},
{"cab": "1717", "type": "Лек", "tch": "Мещеряков А.В.", "name": "Прикладная механика"},
{"cab": "", "type": "", "tch": "", "name": ""},
{"cab": "", "type": "", "tch": "", "name": ""},
{"cab": "", "type": "", "tch": "", "name": ""}
], "fri": [
{"cab": "414", "type": "Пр", "tch": "препод. кафедры", "name": "Физика"},
{"cab": "414", "type": "Лаб", "tch": "препод. кафедры", "name": "Физика"},
{"cab": "413", "type": "Лек", "tch": "Родэ С.В.", "name": "Физика"},
{"cab": "", "type": "", "tch": "", "name": ""},
{"cab": "", "type": "", "tch": "", "name": ""},
{"cab": "", "type": "", "tch": "", "name": ""}
],
"week2": {
"mon": [
{"cab": "510", "type": "Лек", "tch": "Смирнов Е.Е.", "name": "Информационные технологии"},
{"cab": "523", "type": "Лаб", "tch": "Смирнов Е.Е.", "name": "Информационные технологии, п/г 2"},
{"cab": "407", "type": "Пр", "tch": "препод. кафедры", "name": "Иностранный язык"},
{"cab": "515", "type": "Лаб", "tch": "Семенов А.А.", "name": "Информационные системы и технологии в дизайне, п/г 1"},
{"cab": "", "type": "", "tch": "", "name": ""},
{"cab": "", "type": "", "tch": "", "name": ""}
], "tue": [
{"cab": "", "type": "", "tch": "", "name": ""},
{"cab": "510", "type": "Лаб", "tch": "Семенов А.А.", "name": "Технология программирования, п/г 1"},
{"cab": "510", "type": "Лек", "tch": "Семенов А.А.", "name": "Информационные системы и технологии в дизайне"},
{"cab": "510", "type": "Лаб", "tch": "Семенов А.А.", "name": "Информационные системы и технологии в дизайне, п/г 2"},
{"cab": "510", "type": "Лаб", "tch": "Семенов А.А.", "name": "Технология программирования, п/г 2"},
{"cab": "", "type": "", "tch": "", "name": ""}
], "wed": [
{"cab": "", "type": "", "tch": "", "name": ""},
{"cab": "", "type": "", "tch": "", "name": ""},
{"cab": "сп. зал", "type": "пр.", "tch": "преп. каф. физич. культ.", "name": "Элективные дисциплины по физической культуре и спорту"},
{"cab": "1615", "type": "Пр", "tch": "Пухир В.М.", "name": "Философия"},
{"cab": "1611", "type": "Пр", "tch": "Бугримов А.Л.", "name": "Математика"},
{"cab": "", "type": "", "tch": "", "name": ""}
], "thu": [
{"cab": "1537", "type": "Лек", "tch": "Пухир В.М.", "name": "Философия"},
{"cab": "1205", "type": "Лек", "tch": "Суетин В.Ю.", "name": "Математика"},
{"cab": "1210", "type": "Лек", "tch": "Кириенкова В.М.", "name": "Физическая культура и спорт"},
{"cab": "", "type": "", "tch": "", "name": ""},
{"cab": "", "type": "", "tch": "", "name": ""},
{"cab": "", "type": "", "tch": "", "name": ""}
], "fri": [
{"cab": "", "type": "", "tch": "", "name": ""},
{"cab": "414", "type": "Лаб", "tch": "препод. кафедры", "name": "Физика"},
{"cab": "413", "type": "Лек", "tch": "Родэ С.В.", "name": "Физика"},
{"cab": "", "type": "", "tch": "", "name": ""},
{"cab": "", "type": "", "tch": "", "name": ""},
{"cab": "", "type": "", "tch": "", "name": ""}
]}}}