{"week1": {
"mon": [
{"cab": "", "type": "", "tch": "", "name": ""},
{"cab": "", "type": "", "tch": "", "name": "День для самостоятельной работы студентов"},
{"cab": "", "type": "", "tch": "", "name": ""},
{"cab": "", "type": "", "tch": "", "name": ""},
{"cab": "", "type": "", "tch": "", "name": ""},
{"cab": "", "type": "", "tch": "", "name": ""}
], "tue": [
{"cab": "", "type": "", "tch": "", "name": ""},
{"cab": "", "type": "", "tch": "", "name": ""},
{"cab": "6412", "type": "Пр", "tch": "Полиефтова", "name": "Экология"},
{"cab": "6316", "type": "Лек", "tch": "Османов З.Н.", "name": "Экология"},
{"cab": "", "type": "", "tch": "", "name": ""},
{"cab": "", "type": "", "tch": "", "name": ""}
], "wed": [
{"cab": "", "type": "", "tch": "", "name": ""},
{"cab": "1818", "type": "Лек", "tch": "Монахов", "name": "Информационное моделирование"},
{"cab": "1343", "type": "Пр", "tch": "Монахов", "name": "Информационное моделирование"},
{"cab": "1815", "type": "Лек", "tch": "Чесноков А.В.", "name": "Электротехника, электроника"},
{"cab": "1814", "type": "Лаб", "tch": "Иванов М.С.", "name": "Электротехника, электроника, п/г 1"},
{"cab": "", "type": "", "tch": "", "name": ""}
], "thu": [
{"cab": "", "type": "", "tch": "", "name": ""},
{"cab": "1615", "type": "Пр", "tch": "Сельнинова Т.С.", "name": "Экономика и организация производства"},
{"cab": "1125", "type": "Лек", "tch": "Стрельников", "name": "Системное программное обеспечение"},
{"cab": "1615", "type": "Лек", "tch": "Кузьмина", "name": "Дискретная математика"},
{"cab": "1245", "type": "Лаб", "tch": "Стрельников    Федина", "name": "Системное программное обеспечение"},
{"cab": "", "type": "", "tch": "", "name": ""}
], "fri": [
{"cab": "", "type": "", "tch": "", "name": ""},
{"cab": "", "type": "", "tch": "", "name": ""},
{"cab": "сп. зал", "type": "пр.", "tch": "преп. каф. физич. культ.", "name": "Элективные дисциплины по физической культуре и спорту"},
{"cab": "1818", "type": "Лаб", "tch": "Ветрова    Кузьмина", "name": "Компьютерная графика"},
{"cab": "1818", "type": "Пр", "tch": "Кузьмина", "name": "Дискретная математика"},
{"cab": "", "type": "", "tch": "", "name": ""}
],
"week2": {
"mon": [
{"cab": "", "type": "", "tch": "", "name": ""},
{"cab": "", "type": "", "tch": "", "name": ""},
{"cab": "", "type": "", "tch": "", "name": ""},
{"cab": "", "type": "", "tch": "", "name": ""},
{"cab": "", "type": "", "tch": "", "name": ""},
{"cab": "", "type": "", "tch": "", "name": ""}
], "tue": [
{"cab": "1818", "type": "Пр", "tch": "Самойлова", "name": "Схемотехника"},
{"cab": "1703", "type": "Лек", "tch": "Самойлова", "name": "Схемотехника"},
{"cab": "", "type": "", "tch": "", "name": ""},
{"cab": "", "type": "", "tch": "", "name": ""},
{"cab": "", "type": "", "tch": "", "name": ""},
{"cab": "", "type": "", "tch": "", "name": ""}
], "wed": [
{"cab": "", "type": "", "tch": "", "name": ""},
{"cab": "1818", "type": "Пр", "tch": "Ветрова", "name": "Компьютерная графика"},
{"cab": "1615", "type": "Лек", "tch": "Ветрова", "name": "Компьютерная графика"},
{"cab": "1815", "type": "Лек", "tch": "Чесноков А.В.", "name": "Электротехника, электроника"},
{"cab": "1814", "type": "Лаб", "tch": "Иванов М.С.", "name": "Электротехника, электроника, п/г 2"},
{"cab": "", "type": "", "tch": "", "name": ""}
], "thu": [
{"cab": "1327", "type": "", "tch": "", "name": ""},
{"cab": "1537", "type": "Лек", "tch": "Пурыскина В.А.", "name": "Экономика и организация производства"},
{"cab": "1125", "type": "Лек", "tch": "Стрельников", "name": "Системное программное обеспечение"},
{"cab": "1615", "type": "Лек", "tch": "Кузьмина", "name": "Дискретная математика"},
{"cab": "1245", "type": "Лаб", "tch": "Стрельников    Федина", "name": "Системное программное обеспечение"},
{"cab": "", "type": "", "tch": "", "name": ""}
], "fri": [
{"cab": "", "type": "", "tch": "", "name": ""},
{"cab": "", "type": "", "tch": "", "name": ""},
{"cab": "сп. зал", "type": "пр.", "tch": "преп. каф. физич. культ.", "name": "Элективные дисциплины по физической культуре и спорту"},
{"cab": "1818", "type": "Лаб", "tch": "Ветрова    Кузьмина", "name": "Компьютерная графика"},
{"cab": "1818", "type": "Лаб", "tch": "Кузьмина    Ветрова", "name": "Дискретная математика"},
{"cab": "", "type": "", "tch": "", "name": ""}
]}}}